MANIFEST.in
README.md
setup.py
inasafe_core.egg-info/PKG-INFO
inasafe_core.egg-info/SOURCES.txt
inasafe_core.egg-info/dependency_links.txt
inasafe_core.egg-info/requires.txt
inasafe_core.egg-info/top_level.txt
safe/__init__.py
safe/defaults.py
safe/plugin.py
safe/common/__init__.py
safe/common/custom_logging.py
safe/common/dynamic_translations.py
safe/common/exceptions.py
safe/common/minimum_needs.py
safe/common/signals.py
safe/common/utilities.py
safe/common/version.py
safe/common/parameters/__init__.py
safe/common/parameters/default_select_parameter.py
safe/common/parameters/default_select_parameter_widget.py
safe/common/parameters/default_value_parameter.py
safe/common/parameters/default_value_parameter_widget.py
safe/common/parameters/group_select_parameter.py
safe/common/parameters/group_select_parameter_widget.py
safe/common/parameters/percentage_parameter_widget.py
safe/common/parameters/resource_parameter.py
safe/common/parameters/resource_parameter_widget.py
safe/common/parameters/validators.py
safe/common/parameters/test/__init__.py
safe/common/parameters/test/example.py
safe/common/parameters/test/example_group_select.py
safe/common/parameters/test/test_default_select_parameter.py
safe/common/parameters/test/test_default_select_parameter_widget.py
safe/common/parameters/test/test_default_value_parameter.py
safe/common/parameters/test/test_default_value_parameter_widget.py
safe/common/parameters/test/test_group_select_parameter.py
safe/common/parameters/test/test_group_select_parameter_widget.py
safe/common/parameters/test/test_percentage_parameter_widget.py
safe/common/parameters/test/test_resource_parameter.py
safe/common/parameters/test/test_resource_parameter_widget.py
safe/common/test/__init__.py
safe/common/test/test_custom_logging.py
safe/common/test/test_minimum_needs.py
safe/common/test/test_utilities.py
safe/common/test/test_version.py
safe/datastore/__init__.py
safe/datastore/datastore.py
safe/datastore/folder.py
safe/datastore/geopackage.py
safe/datastore/test/__init__.py
safe/datastore/test/test_folder.py
safe/datastore/test/test_geopackage.py
safe/definitions/__init__.py
safe/definitions/analysis_steps.py
